src/__init__.py
src/config_server_play_client.py
src/config_server_python_library.py
config_server_client_python-1.0.2.dist-info/METADATA
config_server_client_python-1.0.2.dist-info/WHEEL
config_server_client_python-1.0.2.dist-info/top_level.txt
config_server_client_python-1.0.2.dist-info/RECORD
