Metadata-Version: 2.1
Name: config-server-client-python
Version: 1.0.2
Summary: Streamline configuration management by fetching and updating configurations from a Spring Cloud Config Server in Python.
Home-page: https://github.com/jayantreddy181198/config-server-client-python
Author: Jayant Reddy
Author-email: jayantreddy181198@gmail.com
